DS/Get_by_dates.py
DS/Loads.py
DS/__init__.py
dfmodule_DSTemplate-0.0.5.dist-info/METADATA
dfmodule_DSTemplate-0.0.5.dist-info/WHEEL
dfmodule_DSTemplate-0.0.5.dist-info/top_level.txt
dfmodule_DSTemplate-0.0.5.dist-info/RECORD
